vrt_lss_agro/__init__.py
vrt_lss_agro/api_client.py
vrt_lss_agro/api_response.py
vrt_lss_agro/configuration.py
vrt_lss_agro/exceptions.py
vrt_lss_agro/py.typed
vrt_lss_agro/rest.py
vrt_lss_agro/api/__init__.py
vrt_lss_agro/api/plan_api.py
vrt_lss_agro/api/system_api.py
vrt_lss_agro/models/__init__.py
vrt_lss_agro/models/attribute.py
vrt_lss_agro/models/bunker.py
vrt_lss_agro/models/calculation_async_result.py
vrt_lss_agro/models/calculation_info.py
vrt_lss_agro/models/calculation_settings.py
vrt_lss_agro/models/calculation_state.py
vrt_lss_agro/models/calculation_status.py
vrt_lss_agro/models/capacity_forecast_element.py
vrt_lss_agro/models/chamber.py
vrt_lss_agro/models/check_result.py
vrt_lss_agro/models/consumer.py
vrt_lss_agro/models/contract.py
vrt_lss_agro/models/contract_type.py
vrt_lss_agro/models/cost_forecast_element.py
vrt_lss_agro/models/crop.py
vrt_lss_agro/models/crop_type.py
vrt_lss_agro/models/custom400_with_errors_and_warnings.py
vrt_lss_agro/models/date_window.py
vrt_lss_agro/models/dryer.py
vrt_lss_agro/models/elevator.py
vrt_lss_agro/models/entity_error.py
vrt_lss_agro/models/entity_error_type.py
vrt_lss_agro/models/entity_path.py
vrt_lss_agro/models/entity_type.py
vrt_lss_agro/models/entity_warning.py
vrt_lss_agro/models/entity_warning_type.py
vrt_lss_agro/models/factory.py
vrt_lss_agro/models/gate.py
vrt_lss_agro/models/general402.py
vrt_lss_agro/models/general404.py
vrt_lss_agro/models/general404_detail.py
vrt_lss_agro/models/general429.py
vrt_lss_agro/models/general500.py
vrt_lss_agro/models/humidity_forecast_element.py
vrt_lss_agro/models/leftover.py
vrt_lss_agro/models/manufacturing_operation.py
vrt_lss_agro/models/market.py
vrt_lss_agro/models/model_field.py
vrt_lss_agro/models/movement_matrix_element.py
vrt_lss_agro/models/object_type.py
vrt_lss_agro/models/operation_measurements.py
vrt_lss_agro/models/operation_target.py
vrt_lss_agro/models/operation_type.py
vrt_lss_agro/models/plan_result.py
vrt_lss_agro/models/plan_settings.py
vrt_lss_agro-7.29.3120.dist-info/METADATA
vrt_lss_agro-7.29.3120.dist-info/WHEEL
vrt_lss_agro-7.29.3120.dist-info/top_level.txt
vrt_lss_agro-7.29.3120.dist-info/RECORD
